latz_imgur/__init__.py
latz_imgur/__version__.py
latz_imgur/main.py
latz_imgur-0.1.2.dist-info/LICENSE
latz_imgur-0.1.2.dist-info/WHEEL
latz_imgur-0.1.2.dist-info/entry_points.txt
latz_imgur-0.1.2.dist-info/METADATA
latz_imgur-0.1.2.dist-info/RECORD
